trading_strategy_tester/__init__.py
trading_strategy_tester/conditions/__init__.py
trading_strategy_tester/conditions/condition.py
trading_strategy_tester/conditions/test_condition.py
trading_strategy_tester/conditions/trade_conditions.py
trading_strategy_tester/conditions/fibonacci_retracement_levels_conditions/__init__.py
trading_strategy_tester/conditions/fibonacci_retracement_levels_conditions/downtrend_fib_retracement_level.py
trading_strategy_tester/conditions/fibonacci_retracement_levels_conditions/uptrend_fib_retracement_level.py
trading_strategy_tester/conditions/logical_conditions/__init__.py
trading_strategy_tester/conditions/logical_conditions/and_condition.py
trading_strategy_tester/conditions/logical_conditions/if_then_else_condition.py
trading_strategy_tester/conditions/logical_conditions/or_condition.py
trading_strategy_tester/conditions/parameterized_conditions/__init__.py
trading_strategy_tester/conditions/parameterized_conditions/after_x_days_condition.py
trading_strategy_tester/conditions/parameterized_conditions/change_of_x_percent_per_y_days_condition.py
trading_strategy_tester/conditions/parameterized_conditions/intra_interval_change_of_x_percent_condition.py
trading_strategy_tester/conditions/stoploss_takeprofit/__init__.py
trading_strategy_tester/conditions/stoploss_takeprofit/stop_loss.py
trading_strategy_tester/conditions/stoploss_takeprofit/take_profit.py
trading_strategy_tester/conditions/threshold_conditions/__init__.py
trading_strategy_tester/conditions/threshold_conditions/cross_over_condition.py
trading_strategy_tester/conditions/threshold_conditions/cross_under_condition.py
trading_strategy_tester/conditions/threshold_conditions/greater_than_condition.py
trading_strategy_tester/conditions/threshold_conditions/less_than_condition.py
trading_strategy_tester/conditions/trend_conditions/__init__.py
trading_strategy_tester/conditions/trend_conditions/downtrend_for_x_days_condition.py
trading_strategy_tester-0.1.7.dist-info/licenses/LICENSE
trading_strategy_tester-0.1.7.dist-info/METADATA
trading_strategy_tester-0.1.7.dist-info/WHEEL
trading_strategy_tester-0.1.7.dist-info/top_level.txt
trading_strategy_tester-0.1.7.dist-info/RECORD
