Metadata-Version: 2.4
Name: trading-strategy-tester
Version: 0.1.7
Summary: Simulate and evaluate trading strategies
Author-email: Daniel Šoltýs <danielsytlos@gmail.com>
License-Expression: MIT
Requires-Python: >=3.10
License-File: LICENSE
Requires-Dist: pandas~=2.2.2
Requires-Dist: numpy~=2.0.1
Requires-Dist: matplotlib
Requires-Dist: plotly~=5.23.0
Requires-Dist: yfinance==0.2.64
Requires-Dist: ollama~=0.4.7
Requires-Dist: pandas_ta~=0.3.14b0
Requires-Dist: deepdiff~=8.4.2
Dynamic: license-file
